JLDracula/__init__.py
JLDracula/_version.py
JLDracula/labextension/package.json
JLDracula/labextension/static/568.37a165d292234396730b.js
JLDracula/labextension/static/747.606c060e66e7fc36c244.js
JLDracula/labextension/static/remoteEntry.6c50a915fc20b9d38473.js
JLDracula/labextension/static/style.js
JLDracula/labextension/static/third-party-licenses.json
JLDracula/labextension/themes/JLDracula/index.css
JLDracula/labextension/themes/JLDracula/index.js
JLDracula-0.2.0.data/data/share/jupyter/labextensions/JLDracula/install.json
JLDracula-0.2.0.data/data/share/jupyter/labextensions/JLDracula/package.json
JLDracula-0.2.0.data/data/share/jupyter/labextensions/JLDracula/static/568.37a165d292234396730b.js
JLDracula-0.2.0.data/data/share/jupyter/labextensions/JLDracula/static/747.606c060e66e7fc36c244.js
JLDracula-0.2.0.data/data/share/jupyter/labextensions/JLDracula/static/remoteEntry.6c50a915fc20b9d38473.js
JLDracula-0.2.0.data/data/share/jupyter/labextensions/JLDracula/static/style.js
JLDracula-0.2.0.data/data/share/jupyter/labextensions/JLDracula/static/third-party-licenses.json
JLDracula-0.2.0.data/data/share/jupyter/labextensions/JLDracula/themes/JLDracula/index.css
JLDracula-0.2.0.data/data/share/jupyter/labextensions/JLDracula/themes/JLDracula/index.js
JLDracula-0.2.0.dist-info/LICENSE
JLDracula-0.2.0.dist-info/METADATA
JLDracula-0.2.0.dist-info/WHEEL
JLDracula-0.2.0.dist-info/top_level.txt
JLDracula-0.2.0.dist-info/RECORD
